setup.py
pymesh/__init__.py
pymesh/base.py
pymesh/obj.py
pymesh/stl.py
pymesh/utils.py
pymesh.egg-info/PKG-INFO
pymesh.egg-info/SOURCES.txt
pymesh.egg-info/dependency_links.txt
pymesh.egg-info/requires.txt
pymesh.egg-info/top_level.txt