Metadata-Version: 1.1
Name: pymesh
Version: 1.0.2
Summary: Library for manipulating (Translate, Rotate and Scale) 3D data using numpy.
Home-page: https://github.com/taxpon/pymesh
Author: Takuro Wada
Author-email: taxpon@gmail.com
License: MIT
Platform: UNKNOWN
Classifier: License :: OSI Approved :: MIT License
Classifier: Programming Language :: Python
